<annotation>
	<folder />
	<filename>-2022-03-14-193549_png_jpg.rf.8e353864b84f3c1684fd25cf89aa57ee.jpg</filename>
	<path>-2022-03-14-193549_png_jpg.rf.8e353864b84f3c1684fd25cf89aa57ee.jpg</path>
	<source>
		<database>roboflow.com</database>
	</source>
	<size>
		<width>640</width>
		<height>640</height>
		<depth>3</depth>
	</size>
	<segmented>0</segmented>
	<object>
		<name>barbell</name>
		<pose>Unspecified</pose>
		<truncated>0</truncated>
		<difficult>0</difficult>
		<occluded>0</occluded>
		<bndbox>
			<xmin>280</xmin>
			<xmax>350</xmax>
			<ymin>409</ymin>
			<ymax>562</ymax>
		</bndbox>
	</object>
	<object>
		<name>barbell</name>
		<pose>Unspecified</pose>
		<truncated>0</truncated>
		<difficult>0</difficult>
		<occluded>0</occluded>
		<bndbox>
			<xmin>520</xmin>
			<xmax>588</xmax>
			<ymin>425</ymin>
			<ymax>583</ymax>
		</bndbox>
	</object>
	<object>
		<name>barbell</name>
		<pose>Unspecified</pose>
		<truncated>0</truncated>
		<difficult>0</difficult>
		<occluded>0</occluded>
		<bndbox>
			<xmin>27</xmin>
			<xmax>97</xmax>
			<ymin>456</ymin>
			<ymax>613</ymax>
		</bndbox>
	</object>
</annotation>