<annotation>
	<folder></folder>
	<filename>63-3-_jpg.rf.6d7943574eb34be9bd19c6e4e14daf24.jpg</filename>
	<path>63-3-_jpg.rf.6d7943574eb34be9bd19c6e4e14daf24.jpg</path>
	<source>
		<database>roboflow.com</database>
	</source>
	<size>
		<width>640</width>
		<height>640</height>
		<depth>3</depth>
	</size>
	<segmented>0</segmented>
	<object>
		<name>barbell</name>
		<pose>Unspecified</pose>
		<truncated>0</truncated>
		<difficult>0</difficult>
		<occluded>0</occluded>
		<bndbox>
			<xmin>50</xmin>
			<xmax>289</xmax>
			<ymin>329</ymin>
			<ymax>641</ymax>
		</bndbox>
	</object>
	<object>
		<name>barbell</name>
		<pose>Unspecified</pose>
		<truncated>0</truncated>
		<difficult>0</difficult>
		<occluded>0</occluded>
		<bndbox>
			<xmin>1</xmin>
			<xmax>83</xmax>
			<ymin>242</ymin>
			<ymax>378</ymax>
		</bndbox>
	</object>
</annotation>
