<annotation>
	<folder />
	<filename>augmented_437_45-3-_jpg.rf.7e3fc44f46cde2f8d21fd341bf8e1d6a.jpg</filename>
	<path>augmented_437_45-3-_jpg.rf.7e3fc44f46cde2f8d21fd341bf8e1d6a.jpg</path>
	<source>
		<database>roboflow.com</database>
	</source>
	<size>
		<width>1300</width>
		<height>866</height>
		<depth>3</depth>
	</size>
	<segmented>0</segmented>
	<object>
		<name>Barbell</name>
		<pose>Unspecified</pose>
		<truncated>0</truncated>
		<difficult>0</difficult>
		<occluded>0</occluded>
		<bndbox>
			<xmin>1151</xmin>
			<xmax>1194</xmax>
			<ymin>721</ymin>
			<ymax>761</ymax>
		</bndbox>
	</object>
</annotation>