<annotation>
	<folder />
	<filename>218-2-_jpg.rf.31251d21e6998ba49b12ff76196391dd.jpg</filename>
	<path>218-2-_jpg.rf.31251d21e6998ba49b12ff76196391dd.jpg</path>
	<source>
		<database>roboflow.com</database>
	</source>
	<size>
		<width>640</width>
		<height>640</height>
		<depth>3</depth>
	</size>
	<segmented>0</segmented>
	<object>
		<name>barbell</name>
		<pose>Unspecified</pose>
		<truncated>0</truncated>
		<difficult>0</difficult>
		<occluded>0</occluded>
		<bndbox>
			<xmin>356</xmin>
			<xmax>567</xmax>
			<ymin>425</ymin>
			<ymax>634</ymax>
		</bndbox>
	</object>
</annotation>