<annotation>
	<folder />
	<filename>augmented_910_64_jpg.rf.af2dcede5253f36a4df3b9977add76cc.jpg</filename>
	<path>augmented_910_64_jpg.rf.af2dcede5253f36a4df3b9977add76cc.jpg</path>
	<source>
		<database>roboflow.com</database>
	</source>
	<size>
		<width>780</width>
		<height>450</height>
		<depth>3</depth>
	</size>
	<segmented>0</segmented>
	<object>
		<name>Barbell</name>
		<pose>Unspecified</pose>
		<truncated>0</truncated>
		<difficult>0</difficult>
		<occluded>0</occluded>
		<bndbox>
			<xmin>110</xmin>
			<xmax>158</xmax>
			<ymin>274</ymin>
			<ymax>328</ymax>
		</bndbox>
	</object>
</annotation>