<annotation>
	<folder></folder>
	<filename>34_jpg.rf.9f3d63a51b75847445383186c05e4c14.jpg</filename>
	<path>34_jpg.rf.9f3d63a51b75847445383186c05e4c14.jpg</path>
	<source>
		<database>roboflow.com</database>
	</source>
	<size>
		<width>640</width>
		<height>640</height>
		<depth>3</depth>
	</size>
	<segmented>0</segmented>
	<object>
		<name>barbell</name>
		<pose>Unspecified</pose>
		<truncated>0</truncated>
		<difficult>0</difficult>
		<occluded>0</occluded>
		<bndbox>
			<xmin>425</xmin>
			<xmax>592</xmax>
			<ymin>1</ymin>
			<ymax>241</ymax>
		</bndbox>
	</object>
</annotation>
