<annotation>
	<folder />
	<filename>220_jpg.rf.c1765238b6198dd0c1a9aba3aa87bcd8.jpg</filename>
	<path>220_jpg.rf.c1765238b6198dd0c1a9aba3aa87bcd8.jpg</path>
	<source>
		<database>roboflow.com</database>
	</source>
	<size>
		<width>640</width>
		<height>640</height>
		<depth>3</depth>
	</size>
	<segmented>0</segmented>
	<object>
		<name>barbell</name>
		<pose>Unspecified</pose>
		<truncated>0</truncated>
		<difficult>0</difficult>
		<occluded>0</occluded>
		<bndbox>
			<xmin>27</xmin>
			<xmax>238</xmax>
			<ymin>380</ymin>
			<ymax>571</ymax>
		</bndbox>
	</object>
</annotation>